.gitignore
CHANGES.rst
CHANGES.txt
COPYRIGHT.txt
EXTERNALS.txt
LICENSE.txt
README.rst
README.txt
bootstrap.py
buildout.cfg
paster.cfg
setup.py
z3c/__init__.py
z3c.offlinepack.egg-info/PKG-INFO
z3c.offlinepack.egg-info/SOURCES.txt
z3c.offlinepack.egg-info/dependency_links.txt
z3c.offlinepack.egg-info/entry_points.txt
z3c.offlinepack.egg-info/namespace_packages.txt
z3c.offlinepack.egg-info/requires.txt
z3c.offlinepack.egg-info/top_level.txt
z3c.offlinepack.egg-info/zip-safe
z3c/offlinepack/README.txt
z3c/offlinepack/__init__.py
z3c/offlinepack/tests.py