Metadata-Version: 1.1
Name: z3c.offlinepack
Version: 0.3
Summary: Pack ZODB databases without running Zope or ZEO
Home-page: https://github.com/rpatterson/z3c.offlinepack
Author: Ross Patterson
Author-email: me@rpatterson.net
License: ZPL
Keywords: zodb pack
Platform: UNKNOWN
Classifier: Framework :: Plone
Classifier: Framework :: Zope2
Classifier: Framework :: Zope3
Classifier: Programming Language :: Python
Classifier: Topic :: Software Development :: Libraries :: Python Modules
